nicerpdb/__init__.py
nicerpdb/__main__.py
nicerpdb/cli.py
nicerpdb/debugger.py
nicerpdb-0.4.0.dist-info/METADATA
nicerpdb-0.4.0.dist-info/WHEEL
nicerpdb-0.4.0.dist-info/entry_points.txt
nicerpdb-0.4.0.dist-info/top_level.txt
nicerpdb-0.4.0.dist-info/RECORD
