Metadata-Version: 2.4
Name: nicerpdb
Version: 0.4.0
Summary: A TUI frontend for pdb
Requires-Python: >=3.9
Requires-Dist: rich
Requires-Dist: click
